odoo/addons/stock_full_location_reservation/README.rst
odoo/addons/stock_full_location_reservation/__init__.py
odoo/addons/stock_full_location_reservation/__manifest__.py
odoo/addons/stock_full_location_reservation/i18n/it.po
odoo/addons/stock_full_location_reservation/i18n/stock_full_location_reservation.pot
odoo/addons/stock_full_location_reservation/models/__init__.py
odoo/addons/stock_full_location_reservation/models/stock_move.py
odoo/addons/stock_full_location_reservation/models/stock_move_line.py
odoo/addons/stock_full_location_reservation/models/stock_picking.py
odoo/addons/stock_full_location_reservation/models/stock_picking_type.py
odoo/addons/stock_full_location_reservation/readme/CONFIGURE.rst
odoo/addons/stock_full_location_reservation/readme/CONTRIBUTORS.rst
odoo/addons/stock_full_location_reservation/readme/DESCRIPTION.rst
odoo/addons/stock_full_location_reservation/security/groups.xml
odoo/addons/stock_full_location_reservation/static/description/icon.png
odoo/addons/stock_full_location_reservation/static/description/index.html
odoo/addons/stock_full_location_reservation/tests/__init__.py
odoo/addons/stock_full_location_reservation/tests/common.py
odoo/addons/stock_full_location_reservation/tests/test_full_location_reservation.py
odoo/addons/stock_full_location_reservation/views/stock_picking_type_views.xml
odoo/addons/stock_full_location_reservation/views/stock_picking_views.xml
odoo14_addon_stock_full_location_reservation-14.0.1.0.1.dev4.dist-info/METADATA
odoo14_addon_stock_full_location_reservation-14.0.1.0.1.dev4.dist-info/WHEEL
odoo14_addon_stock_full_location_reservation-14.0.1.0.1.dev4.dist-info/top_level.txt
odoo14_addon_stock_full_location_reservation-14.0.1.0.1.dev4.dist-info/RECORD
